{
  "744204": ["Andaman & Nicobar Islands", "Aberdeen"],
  "744302": ["Andaman & Nicobar Islands", "Campwell Bay"],
  "744301": ["Andaman & Nicobar Islands", "Car Nicobar"],
  "744202": ["Andaman & Nicobar Islands", "Diglipur"],
  "744211": ["Andaman & Nicobar Islands", "Hemlauk"],
  "744209": ["Andaman & Nicobar Islands", "Kadamtala"],
  "744309": ["Andaman & Nicobar Islands", "Kapanga"],
  "744204": ["Andaman & Nicobar Islands", "Mayabandar"],
  "744101": ["Andaman & Nicobar Islands", "Port Blair"],
  "744208": ["Andaman & Nicobar Islands", "Bakultala"],
  "523201": ["Andhra Pradesh", "Addanki"],
  "504001": ["Andhra Pradesh", "Adilabad"],
  "518301": ["Andhra Pradesh", "Adoni"],
  "518543": ["Andhra Pradesh", "Allagada"],
  "532185": ["Andhra Pradesh", "Amadalavalasa"],
  "533201": ["Andhra Pradesh", "Amalapuram"],
  "531001": ["Andhra Pradesh", "Anakpalle"],
  "515001": ["Andhra Pradesh", "Anantapur"],
  "503224": ["Andhra Pradesh", "Armoor"],
  "534134": ["Andhra Pradesh", "Attili"],
  "521121": ["Andhra Pradesh", "Avanigadda"],
  "522101": ["Andhra Pradesh", "Bapatla"],
  "507111": ["Andhra Pradesh", "Bhadrachalam"],
  "534201": ["Andhra Pradesh", "Bhimavaram"],
  "508116": ["Andhra Pradesh", "Bhongir"],
  "532558": ["Andhra Pradesh", "Bobbili"],
  "520002": ["Andhra Pradesh", "Buchinghampet"],
  "517101": ["Andhra Pradesh", "Chandragiri"],
  "522616": ["Andhra Pradesh", "Chilakaluripeta"],
  "523115": ["Andhra Pradesh", "Chirala"],
  "517001": ["Andhra Pradesh", "Chittoor"],
  "531036": ["Andhra Pradesh", "Chodavaram"],
  "516001": ["Andhra Pradesh", "Cuddapah"],
  "524003": ["Andhra Pradesh", "Dargamitta"],
  "516671": ["Andhra Pradesh", "Dharmavaram"],
  "534001": ["Andhra Pradesh", "Eluru"],
  "509125": ["Andhra Pradesh", "Gadwal"],
  "521301": ["Andhra Pradesh", "Gudivada"],
  "524101": ["Andhra Pradesh", "Gudur"],
  "515801": ["Andhra Pradesh", "Guntakal"],
  "522001": ["Andhra Pradesh", "Guntur"],
  "506001": ["Andhra Pradesh", "Hanamkonda"],
  "515201": ["Andhra Pradesh", "Hindupur"],
  "505468": ["Andhra Pradesh", "Huzurabad"],
  "500001": ["Andhra Pradesh", "Hyderabad G.P.O"],
  "500002": ["Andhra Pradesh", "Hyderabad Jubilee"],
  "521333": ["Andhra Pradesh", "Kaikalur"],
  "533001": ["Andhra Pradesh", "Kakinada"],
  "503111": ["Andhra Pradesh", "Kamareddy"],
  "523105": ["Andhra Pradesh", "Kandukur"],
  "523230": ["Andhra Pradesh", "Kanigiri"],
  "505001": ["Andhra Pradesh", "Karimnagar"],
  "524201": ["Andhra Pradesh", "Kavali"],
  "500004": ["Andhra Pradesh", "Khairatabad"],
  "507001": ["Andhra Pradesh", "Khammam"],
  "533233": ["Andhra Pradesh", "Kothapeta"],
  "507101": ["Andhra Pradesh", "Kothgudem Collieries"],
  "534350": ["Andhra Pradesh", "Kovvur"],
  "521001": ["Andhra Pradesh", "Machilipatnam"],
  "509001": ["Andhra Pradesh", "Mahabubnagar"],
  "506101": ["Andhra Pradesh", "Mahbubabad"],
  "504208": ["Andhra Pradesh", "Mancherial"],
  "533308": ["Andhra Pradesh", "Mandapeta"],
  "522203": ["Andhra Pradesh", "Mangalagiri"],
  "523316": ["Andhra Pradesh", "Markapur"],
  "517325": ["Andhra Pradesh", "Masanapalle"],
  "502110": ["Andhra Pradesh", "Medak"],
  "508207": ["Andhra Pradesh", "Mriyalguda"],
  "508001": ["Andhra Pradesh", "Nalgonda"],
  "518501": ["Andhra Pradesh", "Nandyal"],
  "531116": ["Andhra Pradesh", "Narasipatnam"],
  "524126": ["Andhra Pradesh", "Nayudupeta"],
  "524001": ["Andhra Pradesh", "Nellore"],
  "503001": ["Andhra Pradesh", "Nizamabad"],
  "521201": ["Andhra Pradesh", "Nuzuid"],
  "523001": ["Andhra Pradesh", "Ongole"],
  "534260": ["Andhra Pradesh", "Palakol"],
  "517408": ["Andhra Pradesh", "Palmaner"],
  "506164": ["Andhra Pradesh", "Parkal"],
  "532501": ["Andhra Pradesh", "Parvathipuram"],
  "505172": ["Andhra Pradesh", "Peddapalli"],
  "516360": ["Andhra Pradesh", "Proddatur"],
  "516115": ["Andhra Pradesh", "Pulivendla"],
  "516115": ["Andhra Pradesh", "Rajampet"],
  "533101": ["Andhra Pradesh", "Rajamundry"],
  "533255": ["Andhra Pradesh", "Ramachandrapuram"],
  "533342": ["Andhra Pradesh", "Razole"],
  "522265": ["Andhra Pradesh", "Repalle"],
  "533440": ["Andhra Pradesh", "Samalkot"],
  "502001": ["Andhra Pradesh", "Sangareddy"],
  "522403": ["Andhra Pradesh", "Sattenapalle"],
  "500003": ["Andhra Pradesh", "Secunderabad"],
  "532001": ["Andhra Pradesh", "Shrikakulam"],
  "517644": ["Andhra Pradesh", "Shrikalahasti"],
  "502103": ["Andhra Pradesh", "Siddipet"],
  "509301": ["Andhra Pradesh", "Station Jadcheral"],
  "500027": ["Andhra Pradesh", "Station Kachiguda"],
  "508213": ["Andhra Pradesh", "Suryapet"],
  "534101": ["Andhra Pradesh", "Tadepalligudam"],
  "515411": ["Andhra Pradesh", "Tadpatri"],
  "501141": ["Andhra Pradesh", "Tandur"],
  "534211": ["Andhra Pradesh", "Tanuku"],
  "532201": ["Andhra Pradesh", "Tekkali"],
  "522201": ["Andhra Pradesh", "Tenali"],
  "517501": ["Andhra Pradesh", "Tirupati"],
  "500015": ["Andhra Pradesh", "Trimulgherry"],
  "520001": ["Andhra Pradesh", "Vijaywada"],
  "501101": ["Andhra Pradesh", "Vikarabad"],
  "530001": ["Andhra Pradesh", "Visakhapatnam"],
  "531202": ["Andhra Pradesh", "Vizianagaram"],
  "530004": ["Andhra Pradesh", "Waltair R.S."],
  "509103": ["Andhra Pradesh", "Wanaparthy"],
  "506002": ["Andhra Pradesh", "Warangal"],
  "502220": ["Andhra Pradesh", "Zahirabad"],
  "791001": ["Arunachal Pradesh", "Along"],
  "792101": ["Arunachal Pradesh", "Anini"],
  "792120": ["Arunachal Pradesh", "Changlang"],
  "792104": ["Arunachal Pradesh", "Chaokham"],
  "791122": ["Arunachal Pradesh", "Daporizo"],
  "786629": ["Arunachal Pradesh", "Deomali"],
  "790101": ["Arunachal Pradesh", "Dirang"],
  "791112": ["Arunachal Pradesh", "Doimukh"],
  "792102": ["Arunachal Pradesh", "Hayuliyang"],
  "791103": ["Arunachal Pradesh", "Hill top"],
  "791002": ["Arunachal Pradesh", "Ingkiyong"],
  "791111": ["Arunachal Pradesh", "Itanagar G.P.O"],
  "790002": ["Arunachal Pradesh", "Kalkalang"],
  "786630": ["Arunachal Pradesh", "Khousa"],
  "791121": ["Arunachal Pradesh", "Kimin"],
  "786631": ["Arunachal Pradesh", "Langding"],
  "791125": ["Arunachal Pradesh", "Likabili"],
  "791104": ["Arunachal Pradesh", "Mebo"],
  "792051": ["Arunachal Pradesh", "Mechuka"],
  "792122": ["Arunachal Pradesh", "Meeo"],
  "791110": ["Arunachal Pradesh", "Naharlagon"],
  "792123": ["Arunachal Pradesh", "Nampong"],
  "792103": ["Arunachal Pradesh", "Namsai"],
  "791109": ["Arunachal Pradesh", "Nirjuli"],
  "791102": ["Arunachal Pradesh", "Pasighat"],
  "791113": ["Arunachal Pradesh", "Ramkrishna Mission"],
  "792110": ["Arunachal Pradesh", "Roing"],
  "790103": ["Arunachal Pradesh", "Saijussa"],
  "792111": ["Arunachal Pradesh", "Senpura"],
  "790102": ["Arunachal Pradesh", "Seppa"],
  "792055": ["Arunachal Pradesh", "Vijay nagar"],
  "781301": ["Assam", "Barpeta"],
  "783301": ["Assam", "Dhubri"],
  "786001": ["Assam", "Dibrugarh"],
  "781001": ["Assam", "Guwahati"],
  "781014": ["Assam", "Guwahati University"],
  "788710": ["Assam", "Karimganj"],
  "784125": ["Assam", "Mangaldoi"],
  "782001": ["Assam", "Nagaon (Nowgong)"],
  "781335": ["Assam", "Nalbari"],
  "787001": ["Assam", "North Lakhimpur"],
  "785640": ["Assam", "Sibsagar"],
  "788001": ["Assam", "Silchar"],
  "784001": ["Assam", "Tezpur"],
  "786125": ["Assam", "Tinsukia"],
  "802301": ["Bihar", "Arrah"],
  "824101": ["Bihar", "Aurangabad"],
  "814112": ["Bihar", "Baidyanadh Deoghar"],
  "813102": ["Bihar", "Banka"],
  "851101": ["Bihar", "Begusarai"],
  "845438": ["Bihar", "Bettaih"],
  "812001": ["Bihar", "Bhagalpur"],
  "841460": ["Bihar", "Bhattason"],
  "803101": ["Bihar", "Bihar Shariff"],
  "827001": ["Bihar", "Bokaro Steel City"],
  "802101": ["Bihar", "Buzar"],
  "833201": ["Bihar", "Chaibasa"],
  "841301": ["Bihar", "Chapra"],
  "822101": ["Bihar", "Daltonganj"],
  "846004": ["Bihar", "Darbhanga"],
  "826001": ["Bihar", "Dhanbad"],
  "814101": ["Bihar", "Dumka"],
  "823001": ["Bihar", "Gaya"],
  "815301": ["Bihar", "Giridih"],
  "841428": ["Bihar", "Gopalganj"],
  "835207": ["Bihar", "Gumla"],
  "844101": ["Bihar", "Hajipur"],
  "825301": ["Bihar", "Hazaribagh"],
  "834002": ["Bihar", "Hinoo"],
  "854105": ["Bihar", "Kathihar"],
  "846001": ["Bihar", "Laheriasarai"],
  "847211": ["Bihar", "Madhubani"],
  "841418": ["Bihar", "Marhowrah"],
  "811201": ["Bihar", "Monghyr"],
  "845401": ["Bihar", "Motihari"],
  "842001": ["Bihar", "Muzaffarpur"],
  "805110": ["Bihar", "Nawada"],
  "800001": ["Bihar", "Patna G.P.O"],
  "854301": ["Bihar", "Purnea"],
  "829112": ["Bihar", "Ramgarh Cantt."],
  "834001": ["Bihar", "Ranchi"],
  "852201": ["Bihar", "Saharsa"],
  "848101": ["Bihar", "Samastipur"],
  "821115": ["Bihar", "Sasaram"],
  "843301": ["Bihar", "Sitamarhi"],
  "841226": ["Bihar", "Siwan"],
  "380001": ["Calcutta", "Ahmedabad"],
  "364601": ["Calcutta", "Amreli"],
  "388001": ["Calcutta", "Anand"],
  "392001": ["Calcutta", "Bharuch"],
  "364001": ["Calcutta", "Bhavnagar"],
  "370001": ["Calcutta", "Bhuj"],
  "396321": ["Calcutta", "Bilimora"],
  "394601": ["Calcutta", "Bordoli"],
  "364710": ["Calcutta", "Botad"],
  "391110": ["Calcutta", "Dabhoi"],
  "389151": ["Calcutta", "Dahod"],
  "387810": ["Calcutta", "Dholka"],
  "403004": ["Goa", "A.I.O. Donna Paula"],
  "403508": ["Goa", "Aldona"],
  "403603": ["Goa", "Betul"],
  "403711": ["Goa", "Chikhli"],
  "403504": ["Goa", "Dhampur"],
  "403705": ["Goa", "Dicholi"],
  "403515": ["Goa", "Kandoli"],
  "403710": ["Goa", "Kantolim"],
  "403712": ["Goa", "Kasavali"],
  "403410": ["Goa", "Kavlem"],
  "403705": ["Goa", "Kuvep"],
  "403728": ["Goa", "Loleim"],
  "403723": ["Goa", "Majorda"],
  "403601": ["Goa", "Mandgaon G.P.O"],
  "403507": ["Goa", "Mepusa"],
  "403803": ["Goa", "Murgaon"],
  "403104": ["Goa", "Nevare"],
  "403604": ["Goa", "Nuvem"],
  "403711": ["Goa", "Panaji G.P.O"],
  "403005": ["Goa", "Santacruz"],
  "403103": ["Goa", "Shiroda"],
  "403517": ["Goa", "Shivali"],
  "403406": ["Goa", "Tisk"],
  "403802": ["Goa", "Vasco Da Gama"],
  "412212": ["Goa", "Vela"],
  "385535": ["Gujarat", "Disa"],
  "382010": ["Gujarat", "Gandhi Nagar"],
  "389001": ["Gujarat", "Godhra"],
  "360311": ["Gujarat", "Gondal"],
  "383001": ["Gujarat", "Himat Nagar"],
  "382721": ["Gujarat", "Kalol"],
  "361305": ["Gujarat", "Khambhalia"],
  "387411": ["Gujarat", "Kheda"],
  "383315": ["Gujarat", "Madasa"],
  "384001": ["Gujarat", "Mahesana"],
  "370465": ["Gujarat", "Mandvi"],
  "363641": ["Gujarat", "Morbi"],
  "387001": ["Gujarat", "Nadiad"],
  "380009": ["Gujarat", "Navrangpura"],
  "396445": ["Gujarat", "Navsari"],
  "385001": ["Gujarat", "Palanpur"],
  "384265": ["Gujarat", "Patan"],
  "360575": ["Gujarat", "Porbandar"],
  "360001": ["Gujarat", "Rajkot"],
  "380002": ["Gujarat", "Revdi Bazaar"],
  "395003": ["Gujarat", "Surat"],
  "363001": ["Gujarat", "Surendra Nagar"],
  "384170": ["Gujarat", "Unjha"],
  "390001": ["Gujarat", "Vadodara"],
  "382870": ["Gujarat", "Vajapur"],
  "396001": ["Gujarat", "Valsad"],
  "362265": ["Gujarat", "Veraval"],
  "384315": ["Gujarat", "Visnagar"],
  "133001": ["Haryana", "Ambala Cantt."],
  "133003": ["Haryana", "Ambala City"],
  "125417": ["Haryana", "Bahadurgarh"],
  "125021": ["Haryana", "Bhivani"],
  "121001": ["Haryana", "Faridabad"],
  "124301": ["Haryana", "Gohana"],
  "122001": ["Haryana", "Gurgaon"],
  "125001": ["Haryana", "Hissar"],
  "132001": ["Haryana", "Karnal"],
  "132118": ["Haryana", "Kurukshetra"],
  "123001": ["Haryana", "Narnaul"],
  "132103": ["Haryana", "Panipat"],
  "124001": ["Haryana", "Rohtak"],
  "125055": ["Haryana", "Sirsa"],
  "131001": ["Haryana", "Sonepat"],
  "174305": ["Himachal Pradesh", "Barsar"],
  "174001": ["Himachal Pradesh", "Bilaspur"],
  "176310": ["Himachal Pradesh", "Chamba"],
  "177101": ["Himachal Pradesh", "Dehra Gopipur"],
  "176215": ["Himachal Pradesh", "Dhramsala"],
  "177001": ["Himachal Pradesh", "Hamirpur"],
  "176001": ["Himachal Pradesh", "Kangra"],
  "175101": ["Himachal Pradesh", "Kullu"],
  "175001": ["Himachal Pradesh", "Mandi"],
  "173001": ["Himachal Pradesh", "Nahan"],
  "176061": ["Himachal Pradesh", "Palampur"],
  "172001": ["Himachal Pradesh", "Rampur Bushahr"],
  "172107": ["Himachal Pradesh", "Recong Peo"],
  "171001": ["Himachal Pradesh", "Shimla"],
  "173212": ["Himachal Pradesh", "Solan"],
  "174402": ["Himachal Pradesh", "Sundernagar Township"],
  "174303": ["Himachal Pradesh", "Una"],
  "192101": ["Jammu & Kashmir", "Anantnag"],
  "193101": ["Jammu & Kashmir", "Baramulla"],
  "180004": ["Jammu & Kashmir", "Gandhinagar (Jammu)"],
  "184101": ["Jammu & Kashmir", "Kathua"],
  "194101": ["Jammu & Kashmir", "Leh"],
  "185131": ["Jammu & Kashmir", "Rajouri"],
  "190001": ["Jammu & Kashmir", "Srinagar GPO"],
  "182101": ["Jammu & Kashmir", "Udhampur"],
  "573103": ["Karnataka", "Arsikere"],
  "591304": ["Karnataka", "Athni"],
  "587101": ["Karnataka", "Bagalkot"],
  "591102": ["Karnataka", "Bailhongal"],
  "560002": ["Karnataka", "Bangalore City"],
  "560001": ["Karnataka", "Bangalore G.P.O."],
  "560004": ["Karnataka", "Basavanagudi"],
  "590001": ["Karnataka", "Belgaum"],
  "583101": ["Karnataka", "Bellary"],
  "577301": ["Karnataka", "Bhadravathi"],
  "585401": ["Karnataka", "Bidar"],
  "586101": ["Karnataka", "Bijapur"],
  "571501": ["Karnataka", "Channapatna"],
  "562101": ["Karnataka", "Chickballapur"],
  "577101": ["Karnataka", "Chickmagalur"],
  "591201": ["Karnataka", "Chikodi"],
  "577501": ["Karnataka", "Chitradurga"],
  "577001": ["Karnataka", "Davangere"],
  "580001": ["Karnataka", "Dharwad"],
  "582101": ["Karnataka", "Gadag"],
  "591307": ["Karnataka", "Gokak"],
  "585101": ["Karnataka", "Gulbarga"],
  "560008": ["Karnataka", "HAL II Stage"],
  "583131": ["Karnataka", "Harapanhalli"],
  "573201": ["Karnataka", "Hassan"],
  "581110": ["Karnataka", "Haveri"],
  "583201": ["Karnataka", "Hospet"],
  "580020": ["Karnataka", "Hubli"],
  "591309": ["Karnataka", "Hukeri"],
  "586209": ["Karnataka", "Indi"],
  "574104": ["Karnataka", "Karkala"],
  "581301": ["Karnataka", "Karwar"],
  "563101": ["Karnataka", "Kolar"],
  "571440": ["Karnataka", "Kollegal"],
  "577126": ["Karnataka", "Koppa"],
  "583231": ["Karnataka", "Koppal"],
  "575005": ["Karnataka", "Kulashekar"],
  "581343": ["Karnataka", "Kumta"],
  "576201": ["Karnataka", "Kundapura"],
  "571201": ["Karnataka", "Madikeri"],
  "571401": ["Karnataka", "Mandya"],
  "575001": ["Karnataka", "Mangalore"],
  "576119": ["Karnataka", "Manipal"],
  "586212": ["Karnataka", "Muddebihal"],
  "570001": ["Karnataka", "Mysore"],
  "571301": ["Karnataka", "Nanjangud"],
  "582207": ["Karnataka", "Nargund"],
  "574201": ["Karnataka", "Puttur"],
  "560032": ["Karnataka", "Rabindranath Tagore Nagar"],
  "591317": ["Karnataka", "Raibag"],
  "584101": ["Karnataka", "Raichur"],
  "560010": ["Karnataka", "Rajaji Nagar"],
  "591123": ["Karnataka", "Ramdurg"],
  "581115": ["Karnataka", "Rannebennur"],
  "577401": ["Karnataka", "Sagar (Shinoga)"],
  "570009": ["Karnataka", "Saraswathipuram"],
  "585228": ["Karnataka", "Shahabad"],
  "577201": ["Karnataka", "Shimoga"],
  "585224": ["Karnataka", "Shorapur"],
  "581401": ["Karnataka", "Sirsi"],
  "571438": ["Karnataka", "Srirangapatna"],
  "574239": ["Karnataka", "Sullia"],
  "590006": ["Karnataka", "Tilakwadi East"],
  "572201": ["Karnataka", "Tiptur"],
  "572101": ["Karnataka", "Tumkur"],
  "576101": ["Karnataka", "Udupi"],
  "585201": ["Karnataka", "Yadagiri"],
  "691523": ["Kerala", "Adur"],
  "678541": ["Kerala", "Alathur"],
  "688001": ["Kerala", "Allappuzha"],
  "683101": ["Kerala", "Aluva"],
  "695101": ["Kerala", "Attungal"],
  "680307": ["Kerala", "Chalakudi"],
  "686101": ["Kerala", "Chenganacherry"],
  "689121": ["Kerala", "Chengannur"],
  "688524": ["Kerala", "Cherthala"],
  "682011": ["Kerala", "Ernakulam"],
  "680121": ["Kerala", "Irinjalakuda"],
  "673121": ["Kerala", "Kalpett"],
  "673315": ["Kerala", "Kanhangad"],
  "676121": ["Kerala", "Kanjeri"],
  "686507": ["Kerala", "Kanjirapally"],
  "670001": ["Kerala", "Kannur"],
  "690518": ["Kerala", "Karunagapally"],
  "671121": ["Kerala", "Kasaragod"],
  "685508": ["Kerala", "Kattappana"],
  "690502": ["Kerala", "Kayamkulam"],
  "682001": ["Kerala", "Kochi"],
  "691001": ["Kerala", "Kollam"],
  "691506": ["Kerala", "Kottarakara"],
  "686001": ["Kerala", "Kottayam"],
  "673001": ["Kerala", "Kozhikode"],
  "673020": ["Kerala", "Kozhikode Civil Station"],
  "680503": ["Kerala", "Kunnamkulam"],
  "676505": ["Kerala", "Malappuram"],
  "690101": ["Kerala", "Mavelikara"],
  "686661": ["Kerala", "Muvattupuzha"],
  "695121": ["Kerala", "Neyyattinkara"],
  "678002": ["Kerala", "Olavakkot"],
  "679101": ["Kerala", "Ottapalm"],
  "686575": ["Kerala", "Palai"],
  "678001": ["Kerala", "Palakkad"],
  "689645": ["Kerala", "Pathanamthitta"],
  "683542": ["Kerala", "Perumbavoor"],
  "679577": ["Kerala", "Ponani"],
  "691305": ["Kerala", "Punalur"],
  "673305": ["Kerala", "Quilandy"],
  "670141": ["Kerala", "Taliparamba"],
  "670101": ["Kerala", "Thalassery"],
  "695001": ["Kerala", "Thiruvananthapuram"],
  "685584": ["Kerala", "Thodupuzha"],
  "680001": ["Kerala", "Thrissur"],
  "695014": ["Kerala", "Thycaud"],
  "676101": ["Kerala", "Tirur"],
  "689101": ["Kerala", "Tiruvalla"],
  "680582": ["Kerala", "Vadakancherry"],
  "673101": ["Kerala", "Vadakara"],
  "686141": ["Kerala", "Vaikom"],
  "682302": ["Lakshadweep", "Ambalmukal"],
  "682552": ["Lakshadweep", "Amini"],
  "682551": ["Lakshadweep", "Androth"],
  "682510": ["Lakshadweep", "Ashikkal"],
  "682556": ["Lakshadweep", "Kadnat"],
  "682030": ["Lakshadweep", "Kaknad"],
  "682557": ["Lakshadweep", "Kalpeni"],
  "682529": ["Lakshadweep", "Minicoy"],
  "481001": ["Madhya Pradesh", "Balaghat"],
  "460001": ["Madhya Pradesh", "Betul"],
  "490001": ["Madhya Pradesh", "Bhilai SB"],
  "477001": ["Madhya Pradesh", "Bhind"],
  "462022": ["Madhya Pradesh", "Bhopal BHEL (SB)"],
  "462003": ["Madhya Pradesh", "Bhopal C.I.T. Nagar"],
  "462001": ["Madhya Pradesh", "Bhopal G.P.O"],
  "495001": ["Madhya Pradesh", "Bilaspur"],
  "480001": ["Madhya Pradesh", "Chhaindwara"],
  "471001": ["Madhya Pradesh", "Chhatarpur City"],
  "470661": ["Madhya Pradesh", "Damoh"],
  "475661": ["Madhya Pradesh", "Datia"],
  "455001": ["Madhya Pradesh", "Dewas"],
  "454001": ["Madhya Pradesh", "Dhar"],
  "491001": ["Madhya Pradesh", "Durg"],
  "473001": ["Madhya Pradesh", "Guna"],
  "474001": ["Madhya Pradesh", "Gwalior (Lashkar)"],
  "461001": ["Madhya Pradesh", "Hoshangabad"],
  "452001": ["Madhya Pradesh", "Indore"],
  "494334": ["Madhya Pradesh", "Kanker"],
  "483501": ["Madhya Pradesh", "Katni"],
  "450001": ["Madhya Pradesh", "Khandwa"],
  "451001": ["Madhya Pradesh", "Khargone"],
  "495667": ["Madhya Pradesh", "Korba"],
  "481661": ["Madhya Pradesh", "Mandla"],
  "458001": ["Madhya Pradesh", "Mandsaur"],
  "474006": ["Madhya Pradesh", "Morar"],
  "476001": ["Madhya Pradesh", "Morena"],
  "487001": ["Madhya Pradesh", "Narsinghpur"],
  "458441": ["Madhya Pradesh", "Neemuch"],
  "488001": ["Madhya Pradesh", "Panna"],
  "496001": ["Madhya Pradesh", "Raigarh"],
  "492001": ["Madhya Pradesh", "Raipur"],
  "464551": ["Madhya Pradesh", "Raisen"],
  "465661": ["Madhya Pradesh", "Rajgarh"],
  "491441": ["Madhya Pradesh", "Rajnandgaon"],
  "457001": ["Madhya Pradesh", "Ratlam"],
  "486001": ["Madhya Pradesh", "Rewa"],
  "470001": ["Madhya Pradesh", "Sagar Cantt."],
  "485001": ["Madhya Pradesh", "Santa"],
  "466001": ["Madhya Pradesh", "Sehore"],
  "480661": ["Madhya Pradesh", "Seoni"],
  "484001": ["Madhya Pradesh", "Shahdol"],
  "465001": ["Madhya Pradesh", "Shajapur"],
  "473551": ["Madhya Pradesh", "Shivpuri"],
  "486661": ["Madhya Pradesh", "Sidhi"],
  "472001": ["Madhya Pradesh", "Tikamgarh"],
  "456001": ["Madhya Pradesh", "Ujjain"],
  "464001": ["Madhya Pradesh", "Vidisha"],
  "452004": ["Madhya Pradesh", "Yeshwant Road (Indore)"],
  "414001": ["Maharashtra", "Ahmednagar"],
  "444001": ["Maharashtra", "Akola"],
  "444601": ["Maharashtra", "Amaravati"],
  "431001": ["Maharashtra", "Aurangabad"],
  "443001": ["Maharashtra", "Buldhana"],
  "424101": ["Maharashtra", "Chalisgaon"],
  "442401": ["Maharashtra", "Chandrapur"],
  "400071": ["Maharashtra", "Chembur"],
  "400009": ["Maharashtra", "Chinchbunder"],
  "415605": ["Maharashtra", "Chiplun"],
  "400014": ["Maharashtra", "Dadar"],
  "424001": ["Maharashtra", "Dhule"],
  "400086": ["Maharashtra", "Ghatkoper East"],
  "400004": ["Maharashtra", "Girgaon"],
  "441601": ["Maharashtra", "Gondia"],
  "416115": ["Maharashtra", "Ichalkaranji"],
  "400002": ["Maharashtra", "Kalbadevi"],
  "421301": ["Maharashtra", "Kalyan City"],
  "441001": ["Maharashtra", "Kamptee"],
  "415110": ["Maharashtra", "Karad"],
  "444303": ["Maharashtra", "Khamgaon"],
  "416003": ["Maharashtra", "Kolhapur"],
  "416012": ["Maharashtra", "Kolhapur City"],
  "413512": ["Maharashtra", "Latur"],
  "400016": ["Maharashtra", "Mahim"],
  "423203": ["Maharashtra", "Malegaon town"],
  "416606": ["Maharashtra", "Malvan"],
  "400003": ["Maharashtra", "Mandvi"],
  "403601": ["Maharashtra", "Margo"],
  "416410": ["Maharashtra", "Miraj"],
  "400080": ["Maharashtra", "Mulund"],
  "400001": ["Maharashtra", "Mumbai G.P.O."],
  "400008": ["Maharashtra", "Mumbai central"],
  "444107": ["Maharashtra", "Murtizapur"],
  "440002": ["Maharashtra", "Nagpur City"],
  "440001": ["Maharashtra", "Nagpur G.P.O."],
  "431601": ["Maharashtra", "Nanded"],
  "422001": ["Maharashtra", "Nashik"],
  "422001": ["Maharashtra", "Nashik road"],
  "413501": ["Maharashtra", "Osmanabad"],
  "401404": ["Maharashtra", "Palghar"],
  "403001": ["Maharashtra", "Panagi"],
  "413304": ["Maharashtra", "Pandharpur"],
  "410206": ["Maharashtra", "Panvel"],
  "444805": ["Maharashtra", "Paratwada"],
  "431401": ["Maharashtra", "Parbhani"],
  "400057": ["Maharashtra", "Parleshwar"],
  "411001": ["Maharashtra", "Pune"],
  "411002": ["Maharashtra", "Pune City"],
  "415612": ["Maharashtra", "Ratnagiri"],
  "416416": ["Maharashtra", "Sangli"],
  "415001": ["Maharashtra", "Satara"],
  "416510": ["Maharashtra", "Sawantwadi"],
  "411005": ["Maharashtra", "Shivajinagar Pune"],
  "413709": ["Maharashtra", "Shrirampur"],
  "413001": ["Maharashtra", "Solapur"],
  "400601": ["Maharashtra", "Thane"],
  "442001": ["Maharashtra", "Wardha"],
  "445001": ["Maharashtra", "Yeotamal"],
  "402201": ["Maharashtra", "Alibag"],
  "795126": ["Manipur", "Bishanpur"],
  "795102": ["Manipur", "Chakpirang"],
  "795127": ["Manipur", "Chandel"],
  "795158": ["Manipur", "Chingkompong"],
  "795128": ["Manipur", "Churachandpur"],
  "795143": ["Manipur", "Dhamloan"],
  "788105": ["Manipur", "Giribam"],
  "788115": ["Manipur", "Gular thal"],
  "795001": ["Manipur", "Imphal G.P.O"],
  "795103": ["Manipur", "Kakching bazar"],
  "795122": ["Manipur", "Kala pahad"],
  "795106": ["Manipur", "Karong"],
  "795129": ["Manipur", "Kongkopi"],
  "795010": ["Manipur", "Lamlongbazar"],
  "795004": ["Manipur", "Lamphelpat"],
  "795140": ["Manipur", "Lamsang"],
  "795130": ["Manipur", "Lilong"],
  "795124": ["Manipur", "Loktak Project"],
  "795003": ["Manipur", "Manipurvishwavidyalay"],
  "795002": ["Manipur", "Mantri Pokhri"],
  "795150": ["Manipur", "Mao"],
  "795132": ["Manipur", "Mayang Imphal"],
  "795133": ["Manipur", "Moirang"],
  "795131": ["Manipur", "Morai"],
  "795134": ["Manipur", "Nambol"],
  "795147": ["Manipur", "Nungba"],
  "795114": ["Manipur", "Pagaiyangdong"],
  "795135": ["Manipur", "Palel"],
  "795117": ["Manipur", "Saikot"],
  "795136": ["Manipur", "Sekmai"],
  "795106": ["Manipur", "Senapati"],
  "795139": ["Manipur", "Singghat"],
  "795137": ["Manipur", "Singjamai bazar"],
  "795144": ["Manipur", "Somdal"],
  "795101": ["Manipur", "Sugumu"],
  "795142": ["Manipur", "Ukhrul"],
  "431122": ["Marharashtra", "Beed"],
  "441904": ["Marharashtra", "Bhandara"],
  "425201": ["Marharashtra", "Bhusaval"],
  "400091": ["Marharashtra", "Borivali"],
  "794115": ["Meghalaya", "Ampati"],
  "793011": ["Meghalaya", "Assam rifles"],
  "793002": ["Meghalaya", "Bada bazar"],
  "793103": ["Meghalaya", "Bada pani"],
  "794102": ["Meghalaya", "Baghmara"],
  "793106": ["Meghalaya", "Balat"],
  "794103": ["Meghalaya", "Barega pada"],
  "793101": ["Meghalaya", "Barmihat"],
  "793107": ["Meghalaya", "Bolganj bazar"],
  "793111": ["Meghalaya", "Chera bazar"],
  "793108": ["Meghalaya", "Cherrapunji"],
  "793109": ["Meghalaya", "Dabki"],
  "794005": ["Meghalaya", "Dobasipada"],
  "794105": ["Meghalaya", "Garobandha"],
  "793007": ["Meghalaya", "Happy valley"],
  "793200": ["Meghalaya", "Khilerihat"],
  "793004": ["Meghalaya", "Labaan"],
  "794002": ["Meghalaya", "Labarchandmari"],
  "793010": ["Meghalaya", "Light core peak"],
  "793003": ["Meghalaya", "Lightmukhra"],
  "794112": ["Meghalaya", "Mandi pathar"],
  "793121": ["Meghalaya", "Mawphlang"],
  "793113": ["Meghalaya", "Mosunram"],
  "793114": ["Meghalaya", "Mowkarvat"],
  "793012": ["Meghalaya", "Mowpat"],
  "794107": ["Meghalaya", "Nangalbibra"],
  "793009": ["Meghalaya", "Nanglayer"],
  "793014": ["Meghalaya", "Nangthumai"],
  "793105": ["Meghalaya", "Naya bangla"],
  "793102": ["Meghalaya", "Nongpoh"],
  "793119": ["Meghalaya", "Nongstoin"],
  "793110": ["Meghalaya", "Penursala"],
  "794104": ["Meghalaya", "Phulbari"],
  "793008": ["Meghalaya", "Phutmouri"],
  "794108": ["Meghalaya", "Resubelpada"],
  "794110": ["Meghalaya", "Rongjing"],
  "794114": ["Meghalaya", "Rongra"],
  "793001": ["Meghalaya", "Shillong G.P.O"],
  "793104": ["Meghalaya", "Sumer"],
  "793123": ["Meghalaya", "Umsao"],
  "793122": ["Meghalaya", "Union Christian College"],
  "793006": ["Meghalaya", "Upling"],
  "793005": ["Meghalaya", "Upper Shillong"],
  "794111": ["Meghalaya", "Williamnagar"],
  "796190": ["Mizoram", "Aibok"],
  "796001": ["Mizoram", "Aizawal G.P.O"],
  "796710": ["Mizoram", "Bongmun"],
  "796321": ["Mizoram", "Champhai"],
  "796007": ["Mizoram", "Chandmari"],
  "796770": ["Mizoram", "Chongtai"],
  "796111": ["Mizoram", "Darlawn"],
  "796751": ["Mizoram", "Demgiri"],
  "796310": ["Mizoram", "Khojovai"],
  "796081": ["Mizoram", "Kolosib"],
  "796070": ["Mizoram", "Kowpoi"],
  "796005": ["Mizoram", "Kulokon"],
  "796471": ["Mizoram", "Lakhibera"],
  "796891": ["Mizoram", "Longlai"],
  "796370": ["Mizoram", "Lungdar"],
  "796701": ["Mizoram", "Lunglei"],
  "796730": ["Mizoram", "Lungsein"],
  "796441": ["Mizoram", "Mamit"],
  "796431": ["Mizoram", "Phalaing"],
  "796012": ["Mizoram", "Ramlun"],
  "796501": ["Mizoram", "Rayak"],
  "796901": ["Mizoram", "Saiha"],
  "796410": ["Mizoram", "Sairang"],
  "796261": ["Mizoram", "Saitul"],
  "796810": ["Mizoram", "Sango"],
  "796181": ["Mizoram", "Serchhip"],
  "796075": ["Mizoram", "Thingdol"],
  "796581": ["Mizoram", "Thinghai"],
  "796161": ["Mizoram", "Thingshul Theleha"],
  "796911": ["Mizoram", "Tuipang"],
  "796101": ["Mizoram", "Vairangte"],
  "796009": ["Mizoram", "Vaivakown"],
  "797115": ["Nagaland", "A.R.T.C"],
  "798619": ["Nagaland", "Akulto"],
  "798631": ["Nagaland", "Borholla"],
  "797105": ["Nagaland", "Chaichima"],
  "798603": ["Nagaland", "Champang"],
  "797102": ["Nagaland", "Chijami"],
  "797104": ["Nagaland", "Chochuba"],
  "798614": ["Nagaland", "Chuchaimalang"],
  "797103": ["Nagaland", "Chumukidima"],
  "797112": ["Nagaland", "Dimapur"],
  "798619": ["Nagaland", "Impur"],
  "798611": ["Nagaland", "Kiphir"],
  "797001": ["Nagaland", "Kohima G.P.O"],
  "797106": ["Nagaland", "Maidjiphema"],
  "797114": ["Nagaland", "Mailuri"],
  "798601": ["Nagaland", "Mokokchung"],
  "798621": ["Nagaland", "Mon"],
  "798604": ["Nagaland", "Monkolemba"],
  "798622": ["Nagaland", "Naginimira"],
  "797101": ["Nagaland", "Peren"],
  "797108": ["Nagaland", "Phenk"],
  "797107": ["Nagaland", "Pupterow"],
  "797111": ["Nagaland", "Wokha"],
  "798617": ["Nagaland", "Yonghong"],
  "798620": ["Nagaland", "Zunhebato"],
  "759122": ["Orissa", "Angul"],
  "761110": ["Orissa", "Aska"],
  "754029": ["Orissa", "Athgarh"],
  "767001": ["Orissa", "Balangir"],
  "756001": ["Orissa", "Baleshwar"],
  "768028": ["Orissa", "Bargarh"],
  "757001": ["Orissa", "Baripada"],
  "760001": ["Orissa", "Berhampur"],
  "756110": ["Orissa", "Bhadrak"],
  "761126": ["Orissa", "Bhanjanagar"],
  "766001": ["Orissa", "Bhawani Patana"],
  "751001": ["Orissa", "Bhubaneswar G.P.O"],
  "753002": ["Orissa", "Chandnichowk"],
  "761020": ["Orissa", "Chatrapur"],
  "753001": ["Orissa", "Cuttack"],
  "759001": ["Orissa", "Dhenkanal"],
  "754211": ["Orissa", "Kenndrapara"],
  "758001": ["Orissa", "Keonjargarh"],
  "752055": ["Orissa", "Khurda"],
  "764020": ["Orissa", "Koraput"],
  "752069": ["Orissa", "Nayagarh"],
  "761200": ["Orissa", "Parlakhemudi"],
  "762001": ["Orissa", "Phulbani"],
  "752001": ["Orissa", "Puri"],
  "757043": ["Orissa", "Rairangpur"],
  "765001": ["Orissa", "Rayagada"],
  "769001": ["Orissa", "Rourkela"],
  "768001": ["Orissa", "Sambalpur"],
  "770001": ["Orissa", "Sundargargh"],
  "143001": ["Punjab", "Amritsar"],
  "151001": ["Punjab", "Bathala"],
  "151001": ["Punjab", "Bathinda"],
  "160017": ["Punjab", "Chandigarh"],
  "144205": ["Punjab", "Dasuya"],
  "151203": ["Punjab", "Faridkot"],
  "152001": ["Punjab", "Ferozepur"],
  "143521": ["Punjab", "Gurdaspur"],
  "146001": ["Punjab", "Hoshiarpur"],
  "144601": ["Punjab", "Kapurthala"],
  "141401": ["Punjab", "Khanna"],
  "141001": ["Punjab", "Ludhiana"],
  "142001": ["Punjab", "Moga"],
  "147001": ["Punjab", "Patiala"],
  "144401": ["Punjab", "Phagwara"],
  "140401": ["Punjab", "Rajpura"],
  "140001": ["Punjab", "Rupnagar (Ropar)"],
  "148001": ["Punjab", "Sangrur"],
  "143401": ["Punjab", "Taran Taran"],
  "305001": ["Rajasthan", "Ajmer"],
  "301001": ["Rajasthan", "Alwar"],
  "301701": ["Rajasthan", "Bahror"],
  "327001": ["Rajasthan", "Banswara"],
  "344001": ["Rajasthan", "Barmer"],
  "321401": ["Rajasthan", "Bayana"],
  "305901": ["Rajasthan", "Beawar"],
  "321001": ["Rajasthan", "Bharatpur"],
  "321001": ["Rajasthan", "Bharatpur City"],
  "311001": ["Rajasthan", "Bhilwara"],
  "334001": ["Rajasthan", "Bikaner"],
  "323001": ["Rajasthan", "Bundi"],
  "333026": ["Rajasthan", "Chirawa"],
  "312001": ["Rajasthan", "Chittorgarh"],
  "331001": ["Rajasthan", "Churu"],
  "303301": ["Rajasthan", "Dausa"],
  "321203": ["Rajasthan", "Deeg"],
  "328001": ["Rajasthan", "Dholpur"],
  "341301": ["Rajasthan", "Didwana"],
  "314001": ["Rajasthan", "Dungarpur"],
  "332310": ["Rajasthan", "Fatehpur"],
  "302020": ["Rajasthan", "Gandhinagar (Jaipur)"],
  "322201": ["Rajasthan", "Gangapur R.S"],
  "335512": ["Rajasthan", "Hanumangarh Junction"],
  "322230": ["Rajasthan", "Hindaun"],
  "313324": ["Rajasthan", "Kankroli"],
  "324001": ["Rajasthan", "Kota"],
  "305801": ["Rajasthan", "Madanganj"],
  "341505": ["Rajasthan", "Makrana"],
  "306001": ["Rajasthan", "Marwar Jn."],
  "313203": ["Rajasthan", "Mavli Jn."],
  "341001": ["Rajasthan", "Nagaur"],
  "305601": ["Rajasthan", "Nasirabad"],
  "332713": ["Rajasthan", "Neembathana Town"],
  "324007": ["Rajasthan", "New Grain Mandi (Kota)"],
  "306401": ["Rajasthan", "Pali"],
  "331022": ["Rajasthan", "Ratangarh"],
  "303604": ["Rajasthan", "Sanbhar Lake"],
  "322001": ["Rajasthan", "Sawaimadhopur"],
  "303103": ["Rajasthan", "Shahpura"],
  "302020": ["Rajasthan", "Shastrinagar (Jaipur)"],
  "342003": ["Rajasthan", "Shastrinagar (Jodhpur)"],
  "307001": ["Rajasthan", "Sirohi"],
  "335001": ["Rajasthan", "Sriganganagar"],
  "332715": ["Rajasthan", "Srimadhopur"],
  "304001": ["Rajasthan", "Tonk"],
  "313001": ["Rajasthan", "Udaipur"],
  "737107": ["Sikkim", "Dikchu"],
  "737101": ["Sikkim", "Gangtok G.P.O"],
  "737116": ["Sikkim", "Mangan"],
  "737126": ["Sikkim", "Namchi"],
  "737126": ["Sikkim", "Rangpo"],
  "734224": ["Sikkim", "Tong"],
  "627401": ["Tamil Nadu", "Ambasamudram"],
  "600053": ["Tamil Nadu", "Ambattur"],
  "600002": ["Tamil Nadu", "Anna Road"],
  "631001": ["Tamil Nadu", "Arakkonam"],
  "625016": ["Tamil Nadu", "Arasaradi"],
  "632601": ["Tamil Nadu", "Arni"],
  "626101": ["Tamil Nadu", "Aruppukottai"],
  "636102": ["Tamil Nadu", "Atur"],
  "600054": ["Tamil Nadu", "Avadi Camp"],
  "638301": ["Tamil Nadu", "Bhavani"],
  "625513": ["Tamil Nadu", "Bodinayakanur"],
  "603001": ["Tamil Nadu", "Chengalpattu"],
  "608001": ["Tamil Nadu", "Chidambaram"],
  "638401": ["Tamil Nadu", "Cobichettipalayam"],
  "641001": ["Tamil Nadu", "Coimbatore"],
  "643101": ["Tamil Nadu", "Coonoor"],
  "607001": ["Tamil Nadu", "Cuddalore"],
  "630302": ["Tamil Nadu", "Devakottai"],
  "638656": ["Tamil Nadu", "Dharapuram"],
  "636701": ["Tamil Nadu", "Dharmapuri"],
  "624001": ["Tamil Nadu", "Dindigul"],
  "638001": ["Tamil Nadu", "Erode"],
  "632602": ["Tamil Nadu", "Gudiyattam"],
  "606202": ["Tamil Nadu", "Kallakurichi"],
  "631501": ["Tamil Nadu", "Kanchipuram"],
  "630001": ["Tamil Nadu", "Karaikudi"],
  "639001": ["Tamil Nadu", "Karur"],
  "628501": ["Tamil Nadu", "Kovilpatti"],
  "635001": ["Tamil Nadu", "Krishnagiri"],
  "639104": ["Tamil Nadu", "Kulittalai"],
  "612001": ["Tamil Nadu", "Kumbakonam"],
  "600001": ["Tamil Nadu", "Madras GPO"],
  "625001": ["Tamil Nadu", "Madurai"],
  "630606": ["Tamil Nadu", "Manamadurai"],
  "614001": ["Tamil Nadu", "Mannargudi"],
  "609001": ["Tamil Nadu", "Mayiladuthurai"],
  "612002": ["Tamil Nadu", "Melakaveri"],
  "641301": ["Tamil Nadu", "Mettupalayam"],
  "600004": ["Tamil Nadu", "Mylapore"],
  "629001": ["Tamil Nadu", "Nagercoil"],
  "637001": ["Tamil Nadu", "Namakkal"],
  "611001": ["Tamil Nadu", "Nargarpattinam"],
  "624208": ["Tamil Nadu", "Nilakottai"],
  "624601": ["Tamil Nadu", "Palani"],
  "627002": ["Tamil Nadu", "Palayamkottai"],
  "614205": ["Tamil Nadu", "Papanasam"],
  "623707": ["Tamil Nadu", "Paramakudi"],
  "600003": ["Tamil Nadu", "Park Town"],
  "614601": ["Tamil Nadu", "Pattukottai"],
  "625601": ["Tamil Nadu", "Periyakulam"],
  "642001": ["Tamil Nadu", "Pollachi"],
  "605001": ["Tamil Nadu", "Pondicherry"],
  "622001": ["Tamil Nadu", "Pudukottai"],
  "626117": ["Tamil Nadu", "Rajapalayam"],
  "623501": ["Tamil Nadu", "Ramanathapuram"],
  "632401": ["Tamil Nadu", "Ranipet"],
  "641002": ["Tamil Nadu", "Rathinasabapathipuram"],
  "636001": ["Tamil Nadu", "Salem"],
  "627756": ["Tamil Nadu", "Sankarankoil"],
  "609110": ["Tamil Nadu", "Sirkali"],
  "626123": ["Tamil Nadu", "Sivakasi"],
  "620006": ["Tamil Nadu", "Sri Rangam"],
  "628601": ["Tamil Nadu", "Srivaikuntam"],
  "600016": ["Tamil Nadu", "St.Thomas Mount"],
  "636005": ["Tamil Nadu", "Suramangalam"],
  "625002": ["Tamil Nadu", "Tallakulam"],
  "600045": ["Tamil Nadu", "Tambaram"],
  "627811": ["Tamil Nadu", "Tenkasi"],
  "613001": ["Tamil Nadu", "Thanjavur"],
  "602001": ["Tamil Nadu", "Thiruvallur"],
  "629175": ["Tamil Nadu", "Thuckalay"],
  "621010": ["Tamil Nadu", "Thuraiyur"],
  "621010": ["Tamil Nadu", "Thuraiyur"],
  "600017": ["Tamil Nadu", "Thyagaraynagar"],
  "604001": ["Tamil Nadu", "Tindivanam"],
  "628215": ["Tamil Nadu", "Tiruchendur"],
  "637211": ["Tamil Nadu", "Tiruchengudo"],
  "620001": ["Tamil Nadu", "Tiruchirappalli"],
  "605757": ["Tamil Nadu", "Tirukkoyilur"],
  "627001": ["Tamil Nadu", "Tirunelveli"],
  "635601": ["Tamil Nadu", "Tiruppattur"],
  "641601": ["Tamil Nadu", "Tirupur"],
  "614713": ["Tamil Nadu", "Tiruthuraipundi"],
  "606601": ["Tamil Nadu", "Tiruvannamalai"],
  "610001": ["Tamil Nadu", "Tiruvarur"],
  "628001": ["Tamil Nadu", "Turiyur"],
  "643001": ["Tamil Nadu", "Udagamandalam"],
  "642126": ["Tamil Nadu", "Udamalpet"],
  "632001": ["Tamil Nadu", "Vellore"],
  "605602": ["Tamil Nadu", "Villupuram"],
  "626001": ["Tamil Nadu", "Virudhunagar"],
  "799206": ["Tripura", "Bachaibadi"],
  "799005": ["Tripura", "Abhaynagar"],
  "799001": ["Tripura", "Agartala G.P.O"],
  "799101": ["Tripura", "Amarpur"],
  "799101": ["Tripura", "Amarpur"],
  "799289": ["Tripura", "Ambasa"],
  "799108": ["Tripura", "Ampinagar"],
  "799157": ["Tripura", "Anandpur"],
  "799003": ["Tripura", "Arundatinagar"],
  "799119": ["Tripura", "Baghma"],
  "799106": ["Tripura", "Bokshanagar"],
  "799155": ["Tripura", "Bolomia"],
  "799251": ["Tripura", "Chandrapur"],
  "799107": ["Tripura", "Chareelum"],
  "799250": ["Tripura", "Dharamnagar G.P.O"],
  "799261": ["Tripura", "Kadamtala"],
  "799277": ["Tripura", "Kailashahar"],
  "799203": ["Tripura", "Kalyanpur"],
  "799210": ["Tripura", "Kamalghat"],
  "799285": ["Tripura", "Kamalpur"],
  "799288": ["Tripura", "Kanchanbadi"],
  "799270": ["Tripura", "Kanchanpur"],
  "799132": ["Tripura", "Kathali"],
  "799008": ["Tripura", "Khayerpur"],
  "799201": ["Tripura", "Khowai"],
  "799204": ["Tripura", "Kuli bazar"],
  "799264": ["Tripura", "Kumar ghat"],
  "799006": ["Tripura", "Kunjvan"],
  "799265": ["Tripura", "Makshmara"],
  "799143": ["Tripura", "Manubazar"],
  "799275": ["Tripura", "Manughat"],
  "799159": ["Tripura", "Mati"],
  "799115": ["Tripura", "Melaghar"],
  "799211": ["Tripura", "Mohanpur"],
  "799142": ["Tripura", "Mohripur"],
  "799263": ["Tripura", "Paicharthal"],
  "799279": ["Tripura", "Paitur Bazar"],
  "799277": ["Tripura", "Pani Chowki Bazar"],
  "799260": ["Tripura", "Pani Sagar"],
  "799290": ["Tripura", "Phatikarai"],
  "799214": ["Tripura", "Phatikchara"],
  "799153": ["Tripura", "Radhanagar"],
  "799158": ["Tripura", "Rajnagar"],
  "799002": ["Tripura", "Ramnagar"],
  "799145": ["Tripura", "Shabroom"],
  "799278": ["Tripura", "Shalima"],
  "799213": ["Tripura", "Shatchand"],
  "799213": ["Tripura", "Simra"],
  "799131": ["Tripura", "Sunamura"],
  "799205": ["Tripura", "Telimura"],
  "799256": ["Tripura", "Tripuradam Chera"],
  "799015": ["Tripura", "Vimangad"],
  "282001": ["Uttar Pradesh", "Agra"],
  "282003": ["Uttar Pradesh", "Agra Fort"],
  "224122": ["Uttar Pradesh", "Akbarpur"],
  "202001": ["Uttar Pradesh", "Aligarh"],
  "211001": ["Uttar Pradesh", "Allahabad"],
  "211003": ["Uttar Pradesh", "Allahabad City"],
  "211002": ["Uttar Pradesh", "Allahabad Kacheri"],
  "263601": ["Uttar Pradesh", "Almora"],
  "206122": ["Uttar Pradesh", "Auraiya"],
  "276001": ["Uttar Pradesh", "Azamgarh"],
  "271801": ["Uttar Pradesh", "Bahraich"],
  "277001": ["Uttar Pradesh", "Ballia"],
  "271201": ["Uttar Pradesh", "Balrampur"],
  "210001": ["Uttar Pradesh", "Banda"],
  "272153": ["Uttar Pradesh", "Bansi"],
  "225001": ["Uttar Pradesh", "Barabanki"],
  "250611": ["Uttar Pradesh", "Baraut"],
  "243001": ["Uttar Pradesh", "Bareilly"],
  "272001": ["Uttar Pradesh", "Basti"],
  "246701": ["Uttar Pradesh", "Bijnor"],
  "243601": ["Uttar Pradesh", "Budaun"],
  "203001": ["Uttar Pradesh", "Bulandshahar"],
  "248001": ["Uttar Pradesh", "Dehradun"],
  "248003": ["Uttar Pradesh", "Dehradun Cantt."],
  "274001": ["Uttar Pradesh", "Deoria"],
  "246761": ["Uttar Pradesh", "Dhampur"],
  "207001": ["Uttar Pradesh", "Etah"],
  "206001": ["Uttar Pradesh", "Etawah"],
  "224001": ["Uttar Pradesh", "Faizabad"],
  "209601": ["Uttar Pradesh", "Fatehgarh"],
  "212601": ["Uttar Pradesh", "Fatehpur"],
  "283203": ["Uttar Pradesh", "Firozabad"],
  "201001": ["Uttar Pradesh", "Ghaziabad"],
  "233001": ["Uttar Pradesh", "Ghazipur"],
  "271001": ["Uttar Pradesh", "Gonda"],
  "246401": ["Uttar Pradesh", "Gopeshwar"],
  "273001": ["Uttar Pradesh", "Gorakhpur"],
  "263139": ["Uttar Pradesh", "Haldwani"],
  "210301": ["Uttar Pradesh", "Hamirpur"],
  "245101": ["Uttar Pradesh", "Hapur"],
  "241001": ["Uttar Pradesh", "Hardoi"],
  "208001": ["Uttar Pradesh", "Kanpur"],
  "208004": ["Uttar Pradesh", "Kanpur Cantt."],
  "262701": ["Uttar Pradesh", "Kheri"],
  "203131": ["Uttar Pradesh", "Khurja"],
  "273008": ["Uttar Pradesh", "Kunraghat"],
  "229206": ["Uttar Pradesh", "Lalganj"],
  "284403": ["Uttar Pradesh", "Lalitpur"],
  "246155": ["Uttar Pradesh", "Landsdowne"],
  "226003": ["Uttar Pradesh", "Lucknow Chowk"],
  "226001": ["Uttar Pradesh", "Lucknow GPO"],
  "248110": ["Uttar Pradesh", "Madhobewala"],
  "205001": ["Uttar Pradesh", "Mainpuri"],
  "281001": ["Uttar Pradesh", "Mathura"],
  "275101": ["Uttar Pradesh", "Mau Nath Bhanjan"],
  "250001": ["Uttar Pradesh", "Meerut"],
  "250002": ["Uttar Pradesh", "Meerut City"],
  "231001": ["Uttar Pradesh", "Mirzapur"],
  "244001": ["Uttar Pradesh", "Moradabad"],
  "251001": ["Uttar Pradesh", "Muzaffarnagar"],
  "263001": ["Uttar Pradesh", "Nainital"],
  "208002": ["Uttar Pradesh", "Nawabganj"],
  "285001": ["Uttar Pradesh", "Orai"],
  "274304": ["Uttar Pradesh", "Padrauna"],
  "246001": ["Uttar Pradesh", "Pauri"],
  "262001": ["Uttar Pradesh", "Pilibhit"],
  "262501": ["Uttar Pradesh", "Pithoragarh"],
  "230001": ["Uttar Pradesh", "Pratapgarh"],
  "229001": ["Uttar Pradesh", "Rae Bareli"],
  "244901": ["Uttar Pradesh", "Rampur"],
  "263645": ["Uttar Pradesh", "Ranikhet"],
  "221712": ["Uttar Pradesh", "Rasra"],
  "247667": ["Uttar Pradesh", "Roorkee"],
  "247001": ["Uttar Pradesh", "Saharnpur"],
  "241204": ["Uttar Pradesh", "Sandila"],
  "242001": ["Uttar Pradesh", "Shahjahanpur"],
  "247776": ["Uttar Pradesh", "Shamli"],
  "261001": ["Uttar Pradesh", "Sitapur"],
  "228001": ["Uttar Pradesh", "Sultanpur"],
  "249001": ["Uttar Pradesh", "Tehri"],
  "209801": ["Uttar Pradesh", "Unnao"],
  "221002": ["Uttar Pradesh", "Varanasi"],
  "232329": ["Uttar Pradesh", "Zamania"],
  "244221": ["Uttar Pradesh", "Amroha"],
  "700027": ["West Bengal", "Alipur"],
  "712601": ["West Bengal", "Arambagh"],
  "713301": ["West Bengal", "Asansol"],
  "733101": ["West Bengal", "Balurghat"],
  "722101": ["West Bengal", "Bankura"],
  "700007": ["West Bengal", "Barabazar"],
  "743201": ["West Bengal", "Barasat"],
  "743101": ["West Bengal", "Barrackpore"],
  "743302": ["West Bengal", "Baruipur"],
  "743411": ["West Bengal", "Basirhat"],
  "700010": ["West Bengal", "Beleghata"],
  "700056": ["West Bengal", "Belgharia"],
  "742101": ["West Bengal", "Berhampur"],
  "713101": ["West Bengal", "Burdwan"],
  "700001": ["West Bengal", "Calcutta G.P.O"],
  "712101": ["West Bengal", "Chinsurah"],
  "721401": ["West Bengal", "Contai"],
  "736101": ["West Bengal", "Cooch Behar"],
  "700002": ["West Bengal", "Cossipore"],
  "734101": ["West Bengal", "Darjeeling"],
  "743331": ["West Bengal", "Diamond Harbour"],
  "741101": ["West Bengal", "Drishnapur"],
  "713201": ["West Bengal", "Durgapur"],
  "737101": ["West Bengal", "Gangtok"],
  "711101": ["West Bengal", "Howrah"],
  "742137": ["West Bengal", "Kandi"],
  "713130": ["West Bengal", "Katwa"],
  "732101": ["West Bengal", "Malda"],
  "735221": ["West Bengal", "Mall"],
  "721101": ["West Bengal", "Midnapore"],
  "741302": ["West Bengal", "Nabadwip"],
  "744101": ["West Bengal", "Purulai"],
  "742225": ["West Bengal", "Raghunathganj"],
  "731224": ["West Bengal", "Rampurhat"],
  "741201": ["West Bengal", "Ranaghat"],
  "713347": ["West Bengal", "Raniganj"],
  "711106": ["West Bengal", "Salkia"],
  "712201": ["West Bengal", "Serampore"],
  "497001": ["Chhattisgarh", "Ambikapur"]
}